questradeapi/__init__.py
questradeapi/api.py
questradeapi/request.py
questradeapi/session.py
questradeapi/utils.py
questradeapi-0.0.10.dist-info/METADATA
questradeapi-0.0.10.dist-info/RECORD
questradeapi-0.0.10.dist-info/WHEEL
questradeapi-0.0.10.dist-info/top_level.txt
