Metadata-Version: 2.1
Name: questradeapi
Version: 0.0.10
Summary: Python wrapper for the Questrade API
Home-page: https://github.com/antoineviscardi/questradeapi
Author: Antoine Viscardi
Author-email: antoine.viscardi@gmail.com
License: MIT
Platform: UNKNOWN
Classifier: Programming Language :: Python :: 3
Classifier: License :: OSI Approved :: MIT License
Classifier: Operating System :: OS Independent
